downloader.py
tubetracks_gui.py
plugins/__init__.py
plugins/base.py
plugins/dailymotion.py
plugins/instagram.py
plugins/reddit.py
plugins/soundcloud.py
plugins/spotify.py
plugins/tiktok.py
plugins/twitch.py
plugins/vimeo.py
plugins/youtube.py
tubetracks-1.5.1.dist-info/licenses/LICENSE
tubetracks-1.5.1.dist-info/METADATA
tubetracks-1.5.1.dist-info/WHEEL
tubetracks-1.5.1.dist-info/entry_points.txt
tubetracks-1.5.1.dist-info/top_level.txt
tubetracks-1.5.1.dist-info/RECORD
