Metadata-Version: 2.4
Name: tubetracks
Version: 1.5.1
Summary: TubeTracks: Enhanced YouTube to MP3 Downloader with multi-platform support
Author-email: TubeTracks <hayk.jomardyan@outlook.com>
Maintainer: jomardyan
Project-URL: Homepage, https://github.com/jomardyan/TubeTracks
Project-URL: Repository, https://github.com/jomardyan/TubeTracks.git
Project-URL: Bug Tracker, https://github.com/jomardyan/TubeTracks/issues
Project-URL: Documentation, https://github.com/jomardyan/TubeTracks/blob/main/README.md
Project-URL: Changelog, https://github.com/jomardyan/TubeTracks/blob/main/CHANGELOG.md
Keywords: youtube,mp3,download,audio,yt-dlp,tiktok,instagram,soundcloud,spotify,twitch,media-downloader,audio-converter,tubetracks
Classifier: Development Status :: 4 - Beta
Classifier: Environment :: Console
Classifier: Intended Audience :: End Users/Desktop
Classifier: License :: OSI Approved :: GNU General Public License v3 or later (GPLv3+)
Classifier: Natural Language :: English
Classifier: Operating System :: OS Independent
Classifier: Operating System :: POSIX :: Linux
Classifier: Operating System :: MacOS
Classifier: Operating System :: Microsoft :: Windows
Classifier: Programming Language :: Python :: 3
Classifier: Programming Language :: Python :: 3.8
Classifier: Programming Language :: Python :: 3.9
Classifier: Programming Language :: Python :: 3.10
Classifier: Programming Language :: Python :: 3.11
Classifier: Programming Language :: Python :: 3.12
Classifier: Programming Language :: Python :: Implementation :: CPython
Classifier: Topic :: Desktop Environment
Classifier: Topic :: Multimedia :: Sound/Audio
Classifier: Topic :: Multimedia :: Video
Classifier: Topic :: Internet
Classifier: Topic :: Utilities
Requires-Python: >=3.8
License-File: LICENSE
Requires-Dist: yt-dlp>=2024.0.0
Requires-Dist: rich>=13.0.0
Provides-Extra: dev
Requires-Dist: pytest>=7.0.0; extra == "dev"
Requires-Dist: pytest-cov>=4.0.0; extra == "dev"
Requires-Dist: black>=23.0.0; extra == "dev"
Requires-Dist: isort>=5.0.0; extra == "dev"
Requires-Dist: ruff>=0.1.0; extra == "dev"
Requires-Dist: bandit>=1.7.5; extra == "dev"
Requires-Dist: build>=0.10.0; extra == "dev"
Requires-Dist: twine>=4.0.0; extra == "dev"
Dynamic: license-file
